aiopandas/__init__.py
aiopandas-0.0.3.dist-info/LICENSE
aiopandas-0.0.3.dist-info/METADATA
aiopandas-0.0.3.dist-info/WHEEL
aiopandas-0.0.3.dist-info/top_level.txt
aiopandas-0.0.3.dist-info/RECORD
