Metadata-Version: 2.2
Name: aiopandas
Version: 0.0.3
Summary: Lightweight Pandas monkey-patch for async map, apply, transform, etc.
Author-email: Elias Neuman <elias@payperrun.com>
License: MIT
Project-URL: Homepage, https://github.com/telekinesis-inc/aiopandas
Classifier: Programming Language :: Python :: 3
Classifier: License :: OSI Approved :: MIT License
Classifier: Operating System :: OS Independent
Requires-Python: >=3.7
License-File: LICENSE
Requires-Dist: pandas
